Workbook

Sheet 1_Annahmen
A1: SKIPILY – Marktannahmen & Modellparameter (gelbe Zellen = Inputs)
A3: Markt
A4: Adressierbare Bootseigner DACH | B4: 500000 | C4: BVWW / ADAC
A5: Adressierbare Bootseigner EU+UK | B5: 6000000 | C5: ICOMIA 2023
A6: Service-Provider DACH | B6: 12000 | C6: Marinas, Werften, Sailmaker, Rigger, Chandlery
A7: Service-Provider EU | B7: 95000 | C7: ICOMIA
A8: Marktdurchdringung Ziel Jahr 5 (Privat) | B8: 0.012 | C8: 1.2% – ambitioniert
A10: User-Konversion
A11: Free → Plus Konversionsrate | B11: 0.04 | C11: Strava 4-6%, Komoot 3-5%
A12: Free → Pro Konversionsrate | B12: 0.01 | C12: Power-User
A13: Monatliche Churn Privat | B13: 0.03 | C13: saisonbedingt
A14: Monatliche Churn Provider | B14: 0.02 | C14: B2B SaaS Benchmark
A16: Akquisitionskosten (CAC)
A17: CAC Privat-User (Free) | B17: 4 | C17: Performance Marketing
A18: CAC Privat-User (Paid Conversion) | B18: 18 | C18: Blended
A19: CAC Service-Provider | B19: 240 | C19: Outbound Sales + Field
A21: Variable Pro-User-Kosten / Monat
A22: Cloud/Storage pro aktivem User (€/Monat) | B22: 0.12 | C22: Supabase + S3 + Maps
A23: Support-Kosten pro zahlendem User (€/Monat) | B23: 0.18 | C23: Tickets + Tooling
A24: App Store Gebühr Jahr 1 | B24: 0.3 | C24: Apple/Google Standard
A25: App Store Gebühr ab Jahr 2 | B25: 0.15 | C25: Apple Small Business
A26: Payment-Provider-Gebühr (%) | B26: 0.029 | C26: Stripe
A27: Shop-Provision auf vermittelte Käufe | B27: 0.1 | C27: 10%
A28: Buchungs-Provision auf Marina/Service | B28: 0.05 | C28: 5%
A30: HINWEIS: Alle gelben Zellen sind Annahmen – einfach ändern, das gesamte Modell rechnet automatisch nach.

Sheet 2_Pricing
A1: PRICING-STRATEGIE: Privat-User & Service-Provider
A3: Privat-User (B2C, Freemium)
A4: Tier | B4: Preis/Monat | C4: Preis/Jahr | D4: Ø Blended €/Mon | E4: Zielgruppe
A5: Free | B5: 0 | C5: 0 | D5: =B5*0.6+(C5/12)*0.4 -> 0 | E5: Einsteiger / Lead-Gen
A6: Skipily Plus | B6: 4.99 | C6: 49 | D6: =B6*0.6+(C6/12)*0.4 -> 4.6273333 | E6: Hobby-Skipper, 1-2 Boote
A7: Skipily Pro | B7: 9.99 | C7: 99 | D7: =B7*0.6+(C7/12)*0.4 -> 9.294 | E7: Eigner-Profis, Mehrboot, Charterer
A9: Service-Provider (B2B SaaS + Provisionen)
A10: Tier | B10: Preis/Monat | C10: Preis/Jahr | D10: Ø Blended €/Mon | E10: Inhalte
A11: Basic Listing | B11: 0 | C11: 0 | D11: =B11*0.5+(C11/12)*0.5 -> 0 | E11: Verifiziertes Profil, Map-Pin (Lead-Gen)
A12: Provider Starter | B12: 29 | C12: 290 | D12: =B12*0.5+(C12/12)*0.5 -> 26.583333 | E12: Foto-Galerie, 5 Promos/Mon, Reviews
A13: Provider Pro | B13: 79 | C13: 790 | D13: =B13*0.5+(C13/12)*0.5 -> 72.416667 | E13: Unlimited Promos, Shop, Analytics, Top-Placement
A14: Provider Enterprise | B14: 199 | C14: 1990 | D14: =B14*0.5+(C14/12)*0.5 -> 182.41667 | E14: Multi-Location, API, White-Label-Widget
A17: Mix-Annahmen (für Umsatzprognose – änderbar)
A18: Anteil zahlende Privat → Plus | B18: 0.8
A19: Anteil zahlende Privat → Pro | B19: 0.2
A20: Anteil Provider → Starter | B20: 0.55
A21: Anteil Provider → Pro | B21: 0.35
A22: Anteil Provider → Enterprise | B22: 0.1
A24: ARPU/Monat zahlender Privat-User | B24: =D6*B18+D7*B19 -> 5.5606667
A25: ARPU/Monat zahlender Provider | B25: =D12*B20+D13*B21+D14*B22 -> 58.208333

Sheet 3_Investment
A1: INVESTMENT-PLAN (Kapitalbedarf Seed → Series A)
A3: Position / Phase | B3: Jahr 1 | C3: Jahr 2 | D3: Jahr 3 | E3: Jahr 4 | F3: Jahr 5
A4: Phase | B4: MVP & Launch | C4: Scale DACH | D4: EU-Rollout | E4: Konsolidierung | F4: Profit
A5: Produktentwicklung (iOS, Backend, Web) | B5: 220000 | C5: 320000 | D5: 380000 | E5: 420000 | F5: 380000
A6: Design & UX | B6: 45000 | C6: 60000 | D6: 70000 | E6: 70000 | F6: 60000
A7: Cloud, Tools, Lizenzen, Software | B7: 18000 | C7: 35000 | D7: 60000 | E7: 90000 | F7: 120000
A8: Marketing & User-Akquise | B8: 60000 | C8: 180000 | D8: 350000 | E8: 420000 | F8: 350000
A9: Sales (Outbound Provider-Akquise) | B9: 25000 | C9: 90000 | D9: 160000 | E9: 200000 | F9: 180000
A10: Operations / Support | B10: 20000 | C10: 55000 | D10: 110000 | E10: 160000 | F10: 180000
A11: Legal, IP, Compliance, GDPR | B11: 22000 | C11: 18000 | D11: 25000 | E11: 28000 | F11: 25000
A12: Office, Reise, Sonstiges | B12: 15000 | C12: 22000 | D12: 35000 | E12: 40000 | F12: 40000
A13: Buffer / Contingency 10% | B13: 42500 | C13: 78000 | D13: 119000 | E13: 142800 | F13: 133500
A14: Investment p.a. (€) | B14: =SUM(B5:B13) -> 467500 | C14: =SUM(C5:C13) -> 858000 | D14: =SUM(D5:D13) -> 1309000 | E14: =SUM(E5:E13) -> 1570800 | F14: =SUM(F5:F13) -> 1468500
A15: Kumuliert (€) | B15: =B14 -> 467500 | C15: =B15+C14 -> 1325500 | D15: =C15+D14 -> 2634500 | E15: =D15+E14 -> 4205300 | F15: =E15+F14 -> 5673800
A17: FINANZIERUNGS-ROUNDS (typisch)
A18: Round | B18: Zeitpunkt | C18: Volumen (€)
A19: Pre-Seed (Bootstrap + Angels) | B19: Q1 Jahr 1 | C19: 250000
A20: Seed Round | B20: Q4 Jahr 1 | C20: 1500000
A21: Series A | B21: Q2 Jahr 3 | C21: 5000000
A22: Summe Funding | C22: =SUM(C19:C21) -> 6750000

Sheet 4_Kosten
A1: FIXE & VARIABLE BETRIEBSKOSTEN (Jahr 1 – 5)
A3: Position | B3: Jahr 1 | C3: Jahr 2 | D3: Jahr 3 | E3: Jahr 4 | F3: Jahr 5
A4: FIX-KOSTEN (€/Jahr)
A5: Personal Engineering (FTE) | B5: 100000 | C5: 320000 | D5: 480000 | E5: 600000 | F5: 660000
A6: Personal Sales/Marketing (FTE) | B6: 60000 | C6: 140000 | D6: 260000 | E6: 360000 | F6: 380000
A7: Personal Operations/Support (FTE) | B7: 30000 | C7: 80000 | D7: 160000 | E7: 220000 | F7: 260000
A8: Geschäftsführung | B8: 80000 | C8: 90000 | D8: 120000 | E8: 140000 | F8: 150000
A9: Büro, Co-Working | B9: 9000 | C9: 18000 | D9: 30000 | E9: 36000 | F9: 42000
A10: Software-Tools (Supabase, Google-API,GitHub Ent., Claude) | B10: 1000 | C10: 14000 | D10: 22000 | E10: 30000 | F10: 36000
A11: Legal, Buchhaltung, Steuerberatung | B11: 18000 | C11: 22000 | D11: 28000 | E11: 32000 | F11: 36000 | H11: =12*20+18*12+25*12 -> 756
A12: Versicherungen (D&O, Cyber) | B12: 3000 | C12: 6000 | D12: 10000 | E12: 14000 | F12: 16000
A13: Marketing-Fixum (SEO, Content, PR) | B13: 12000 | C13: 30000 | D13: 60000 | E13: 80000 | F13: 90000
A14: Σ Fix-Kosten | B14: =SUM(B5:B13) -> 313000 | C14: =SUM(C5:C13) -> 720000 | D14: =SUM(D5:D13) -> 1170000 | E14: =SUM(E5:E13) -> 1512000 | F14: =SUM(F5:F13) -> 1670000
A16: VARIABLE KOSTEN (€/Jahr) – verlinkt aus Umsatzprognose
A17: Cloud / Hosting / Storage | B17: ='5_Umsatz_Prognose'!B26 -> 21600 | C17: ='5_Umsatz_Prognose'!C26 -> 108000 | D17: ='5_Umsatz_Prognose'!D26 -> 316800 | E17: ='5_Umsatz_Prognose'!E26 -> 691200 | F17: ='5_Umsatz_Prognose'!F26 -> 1123200
A18: Customer Support | B18: ='5_Umsatz_Prognose'!B27 -> 1620 | C18: ='5_Umsatz_Prognose'!C27 -> 8100 | D18: ='5_Umsatz_Prognose'!D27 -> 23760 | E18: ='5_Umsatz_Prognose'!E27 -> 51840 | F18: ='5_Umsatz_Prognose'!F27 -> 84240
A19: App-Store-Gebühren (Apple/Google) | B19: ='5_Umsatz_Prognose'!B28 -> 15013.8 | C19: ='5_Umsatz_Prognose'!C28 -> 37534.5 | D19: ='5_Umsatz_Prognose'!D28 -> 110101.2 | E19: ='5_Umsatz_Prognose'!E28 -> 240220.8 | F19: ='5_Umsatz_Prognose'!F28 -> 390358.8
A20: Payment-Provider-Gebühren | B20: ='5_Umsatz_Prognose'!B29 -> 2816.335 | C20: ='5_Umsatz_Prognose'!C29 -> 15483.571 | D20: ='5_Umsatz_Prognose'!D29 -> 53679.667 | E20: ='5_Umsatz_Prognose'!E29 -> 132971.29 | F20: ='5_Umsatz_Prognose'!F29 -> 251597.68
A21: Performance-Marketing CAC Free | B21: ='5_Umsatz_Prognose'!B30 -> 60000 | C21: ='5_Umsatz_Prognose'!C30 -> 240000 | D21: ='5_Umsatz_Prognose'!D30 -> 580000 | E21: ='5_Umsatz_Prognose'!E30 -> 1040000 | F21: ='5_Umsatz_Prognose'!F30 -> 1200000
A22: Aufschlag CAC Paid Conversion | B22: ='5_Umsatz_Prognose'!B31 -> 10500 | C22: ='5_Umsatz_Prognose'!C31 -> 42000 | D22: ='5_Umsatz_Prognose'!D31 -> 101500 | E22: ='5_Umsatz_Prognose'!E31 -> 182000 | F22: ='5_Umsatz_Prognose'!F31 -> 210000
A23: Sales-CAC Provider | B23: ='5_Umsatz_Prognose'!B32 -> 43200 | C23: ='5_Umsatz_Prognose'!C32 -> 112800 | D23: ='5_Umsatz_Prognose'!D32 -> 276000 | E23: ='5_Umsatz_Prognose'!E32 -> 408000 | F23: ='5_Umsatz_Prognose'!F32 -> 480000
A24: Σ Variable Kosten | B24: =SUM(B17:B23) -> 154750.14 | C24: =SUM(C17:C23) -> 563918.07 | D24: =SUM(D17:D23) -> 1461840.9 | E24: =SUM(E17:E23) -> 2746232.1 | F24: =SUM(F17:F23) -> 3739396.5
A26: GESAMT-KOSTEN (Fix + Variabel) | B26: =B14+B24 -> 467750.14 | C26: =C14+C24 -> 1283918.1 | D26: =D14+D24 -> 2631840.9 | E26: =E14+E24 -> 4258232.1 | F26: =F14+F24 -> 5409396.5

Sheet 5_Umsatz_Prognose
A1: UMSATZPROGNOSE 5 JAHRE
A3: Kennzahl | B3: Jahr 1 | C3: Jahr 2 | D3: Jahr 3 | E3: Jahr 4 | F3: Jahr 5
A4: USER-FUNNEL Privat
A5: Free MAU (Jahresende) | B5: 15000 | C5: 75000 | D5: 220000 | E5: 480000 | F5: 780000
A6: Konversion → Plus | B6: ='1_Annahmen'!B11 -> 0.04 | C6: ='1_Annahmen'!B11 -> 0.04 | D6: ='1_Annahmen'!B11 -> 0.04 | E6: ='1_Annahmen'!B11 -> 0.04 | F6: ='1_Annahmen'!B11 -> 0.04
A7: Konversion → Pro | B7: ='1_Annahmen'!B12 -> 0.01 | C7: ='1_Annahmen'!B12 -> 0.01 | D7: ='1_Annahmen'!B12 -> 0.01 | E7: ='1_Annahmen'!B12 -> 0.01 | F7: ='1_Annahmen'!B12 -> 0.01
A8: Zahlende User Plus | B8: =B5*B6 -> 600 | C8: =C5*C6 -> 3000 | D8: =D5*D6 -> 8800 | E8: =E5*E6 -> 19200 | F8: =F5*F6 -> 31200
A9: Zahlende User Pro | B9: =B5*B7 -> 150 | C9: =C5*C7 -> 750 | D9: =D5*D7 -> 2200 | E9: =E5*E7 -> 4800 | F9: =F5*F7 -> 7800
A10: Σ Zahlende Privat-User | B10: =B8+B9 -> 750 | C10: =C8+C9 -> 3750 | D10: =D8+D9 -> 11000 | E10: =E8+E9 -> 24000 | F10: =F8+F9 -> 39000
A12: PROVIDER-FUNNEL
A13: Aktive Provider (gesamt, EOY) | B13: 180 | C13: 650 | D13: 1800 | E13: 3500 | F13: 5500
A14: Anteil zahlend (Starter+Pro+Ent) | B14: 0.3 | C14: 0.45 | D14: 0.55 | E14: 0.62 | F14: 0.68
A15: Σ Zahlende Provider | B15: =B13*B14 -> 54 | C15: =C13*C14 -> 292.5 | D15: =D13*D14 -> 990 | E15: =E13*E14 -> 2170 | F15: =F13*F14 -> 3740
A17: UMSATZ-STRÖME (€/Jahr)
A18: Abo-Umsatz Privat | B18: =B10*'2_Pricing'!B24*12 -> 50046 | C18: =C10*'2_Pricing'!B24*12 -> 250230 | D18: =D10*'2_Pricing'!B24*12 -> 734008 | E18: =E10*'2_Pricing'!B24*12 -> 1601472 | F18: =F10*'2_Pricing'!B24*12 -> 2602392
A19: Abo-Umsatz Provider | B19: =B15*'2_Pricing'!B25*12 -> 37719 | C19: =C15*'2_Pricing'!B25*12 -> 204311.25 | D19: =D15*'2_Pricing'!B25*12 -> 691515 | E19: =E15*'2_Pricing'!B25*12 -> 1515745 | F19: =F15*'2_Pricing'!B25*12 -> 2612390
A20: Shop-Provisionen (10%) | B20: =B10*60*0.8*'1_Annahmen'!B27 -> 3600 | C20: =C10*80*1.5*'1_Annahmen'!B27 -> 45000 | D20: =D10*100*2.5*'1_Annahmen'!B27 -> 275000 | E20: =E10*120*3.5*'1_Annahmen'!B27 -> 1008000 | F20: =F10*140*4.5*'1_Annahmen'!B27 -> 2457000
A21: Buchungs-Provisionen (5%) | B21: =B10*20*'1_Annahmen'!B28 -> 750 | C21: =C10*50*'1_Annahmen'!B28 -> 9375 | D21: =D10*110*'1_Annahmen'!B28 -> 60500 | E21: =E10*200*'1_Annahmen'!B28 -> 240000 | F21: =F10*320*'1_Annahmen'!B28 -> 624000
A22: Sponsored Placements / Ads | B22: 5000 | C22: 25000 | D22: 90000 | E22: 220000 | F22: 380000
A23: GESAMTUMSATZ | B23: =SUM(B18:B22) -> 97115 | C23: =SUM(C18:C22) -> 533916.25 | D23: =SUM(D18:D22) -> 1851023 | E23: =SUM(E18:E22) -> 4585217 | F23: =SUM(F18:F22) -> 8675782
A25: VARIABLE KOSTEN-DETAIL (€/Jahr)
A26: Cloud-Kosten | B26: =B5*'1_Annahmen'!B22*12 -> 21600 | C26: =C5*'1_Annahmen'!B22*12 -> 108000 | D26: =D5*'1_Annahmen'!B22*12 -> 316800 | E26: =E5*'1_Annahmen'!B22*12 -> 691200 | F26: =F5*'1_Annahmen'!B22*12 -> 1123200
A27: Support-Kosten | B27: =B10*'1_Annahmen'!B23*12 -> 1620 | C27: =C10*'1_Annahmen'!B23*12 -> 8100 | D27: =D10*'1_Annahmen'!B23*12 -> 23760 | E27: =E10*'1_Annahmen'!B23*12 -> 51840 | F27: =F10*'1_Annahmen'!B23*12 -> 84240
A28: App-Store-Gebühren | B28: =B18*'1_Annahmen'!B24 -> 15013.8 | C28: =C18*'1_Annahmen'!B25 -> 37534.5 | D28: =D18*'1_Annahmen'!B25 -> 110101.2 | E28: =E18*'1_Annahmen'!B25 -> 240220.8 | F28: =F18*'1_Annahmen'!B25 -> 390358.8
A29: Payment-Gebühren | B29: =B23*'1_Annahmen'!B26 -> 2816.335 | C29: =C23*'1_Annahmen'!B26 -> 15483.571 | D29: =D23*'1_Annahmen'!B26 -> 53679.667 | E29: =E23*'1_Annahmen'!B26 -> 132971.29 | F29: =F23*'1_Annahmen'!B26 -> 251597.68
A30: CAC Privat (Performance-Marketing, neue Free-User × CAC Free) | B30: =B5*'1_Annahmen'!B17 -> 60000 | C30: =MAX(0,C5-B5)*'1_Annahmen'!B17 -> 240000 | D30: =MAX(0,D5-C5)*'1_Annahmen'!B17 -> 580000 | E30: =MAX(0,E5-D5)*'1_Annahmen'!B17 -> 1040000 | F30: =MAX(0,F5-E5)*'1_Annahmen'!B17 -> 1200000
A31: CAC-Aufschlag Paid Conversion (zahlende User × Paid-CAC Aufschlag) | B31: =B10*('1_Annahmen'!B18-'1_Annahmen'!B17) -> 10500 | C31: =MAX(0,C10-B10)*('1_Annahmen'!B18-'1_Annahmen'!B17) -> 42000 | D31: =MAX(0,D10-C10)*('1_Annahmen'!B18-'1_Annahmen'!B17) -> 101500 | E31: =MAX(0,E10-D10)*('1_Annahmen'!B18-'1_Annahmen'!B17) -> 182000 | F31: =MAX(0,F10-E10)*('1_Annahmen'!B18-'1_Annahmen'!B17) -> 210000
A32: CAC Provider (Sales) | B32: =B13*'1_Annahmen'!B19 -> 43200 | C32: =MAX(0,C13-B13)*'1_Annahmen'!B19 -> 112800 | D32: =MAX(0,D13-C13)*'1_Annahmen'!B19 -> 276000 | E32: =MAX(0,E13-D13)*'1_Annahmen'!B19 -> 408000 | F32: =MAX(0,F13-E13)*'1_Annahmen'!B19 -> 480000
A33: Σ Variable Kosten | B33: =SUM(B26:B32) -> 154750.14 | C33: =SUM(C26:C32) -> 563918.07 | D33: =SUM(D26:D32) -> 1461840.9 | E33: =SUM(E26:E32) -> 2746232.1 | F33: =SUM(F26:F32) -> 3739396.5

Sheet 6_GuV_Breakeven
A1: GEWINN- & VERLUSTRECHNUNG + BREAKEVEN-ANALYSE
A3: Position | B3: Jahr 1 | C3: Jahr 2 | D3: Jahr 3 | E3: Jahr 4 | F3: Jahr 5
A4: Umsatz | B4: ='5_Umsatz_Prognose'!B23 -> 97115 | C4: ='5_Umsatz_Prognose'!C23 -> 533916.25 | D4: ='5_Umsatz_Prognose'!D23 -> 1851023 | E4: ='5_Umsatz_Prognose'!E23 -> 4585217 | F4: ='5_Umsatz_Prognose'!F23 -> 8675782
A5: (-) Variable Kosten | B5: =-'5_Umsatz_Prognose'!B33 -> -154750.14 | C5: =-'5_Umsatz_Prognose'!C33 -> -563918.07 | D5: =-'5_Umsatz_Prognose'!D33 -> -1461840.9 | E5: =-'5_Umsatz_Prognose'!E33 -> -2746232.1 | F5: =-'5_Umsatz_Prognose'!F33 -> -3739396.5
A6: Deckungsbeitrag | B6: =B4+B5 -> -57635.135 | C6: =C4+C5 -> -30001.821 | D6: =D4+D5 -> 389182.13 | E6: =E4+E5 -> 1838984.9 | F6: =F4+F5 -> 4936385.5
A7: DB-Marge | B7: =IFERROR(B6/B4,0) -> -0.59347305 | C7: =IFERROR(C6/C4,0) -> -0.056191999 | D7: =IFERROR(D6/D4,0) -> 0.21025246 | E7: =IFERROR(E6/E4,0) -> 0.40106824 | F7: =IFERROR(F6/F4,0) -> 0.5689845
A8: (-) Fixkosten | B8: =-'4_Kosten'!B14 -> -313000 | C8: =-'4_Kosten'!C14 -> -720000 | D8: =-'4_Kosten'!D14 -> -1170000 | E8: =-'4_Kosten'!E14 -> -1512000 | F8: =-'4_Kosten'!F14 -> -1670000
A9: EBITDA | B9: =B6+B8 -> -370635.14 | C9: =C6+C8 -> -750001.82 | D9: =D6+D8 -> -780817.87 | E9: =E6+E8 -> 326984.91 | F9: =F6+F8 -> 3266385.5
A10: EBITDA-Marge | B10: =IFERROR(B9/B4,0) -> -3.8164561 | C10: =IFERROR(C9/C4,0) -> -1.4047181 | D10: =IFERROR(D9/D4,0) -> -0.42183045 | E10: =IFERROR(E9/E4,0) -> 0.071312853 | F10: =IFERROR(F9/F4,0) -> 0.37649465
A12: KAPITALFLUSS & BREAKEVEN
A13: Kumulierter EBITDA | B13: =B9 -> -370635.14 | C13: =B13+C9 -> -1120637 | D13: =C13+D9 -> -1901454.8 | E13: =D13+E9 -> -1574469.9 | F13: =E13+F9 -> 1691915.6
A14: Funding-Zufluss | B14: 1750000 | C14: 0 | D14: 5000000 | E14: 0 | F14: 0
A15: Funding (kumuliert) | B15: =B14 -> 1750000 | C15: =B15+C14 -> 1750000 | D15: =C15+D14 -> 6750000 | E15: =D15+E14 -> 6750000 | F15: =E15+F14 -> 6750000
A16: Cash-Bestand (Funding + kum. EBITDA) | B16: =B15+B13 -> 1379364.9 | C16: =C15+C13 -> 629363.04 | D16: =D15+D13 -> 4848545.2 | E16: =E15+E13 -> 5175530.1 | F16: =F15+F13 -> 8441915.6
A18: BREAKEVEN-UMSATZ je Jahr (Fix / DB-Marge)
A19: Erforderlicher Umsatz für Breakeven | B19: =IFERROR(-B8/IFERROR(B6/B4,0),0) -> -527403.9 | C19: =IFERROR(-C8/IFERROR(C6/C4,0),0) -> -12813212 | D19: =IFERROR(-D8/IFERROR(D6/D4,0),0) -> 5564738.8 | E19: =IFERROR(-E8/IFERROR(E6/E4,0),0) -> 3769932 | F19: =IFERROR(-F8/IFERROR(F6/F4,0),0) -> 2935053.6
A20: Tatsächlicher Umsatz | B20: =B4 -> 97115 | C20: =C4 -> 533916.25 | D20: =D4 -> 1851023 | E20: =E4 -> 4585217 | F20: =F4 -> 8675782
A21: Δ zu Breakeven | B21: =B4-B19 -> 624518.9 | C21: =C4-C19 -> 13347128 | D21: =D4-D19 -> -3713715.8 | E21: =E4-E19 -> 815284.97 | F21: =F4-F19 -> 5740728.4
A23: Breakeven-Jahr (erstes Jahr mit positivem EBITDA): | B23: =IFERROR("Jahr "&MATCH(TRUE,B9:F9>0,0),"nach Jahr 5") -> nach Jahr 5

Sheet 7_Verlauf_Charts
A1: VERLAUFS-DATEN & DIAGRAMME
A3: Jahr | B3: Jahr 1 | C3: Jahr 2 | D3: Jahr 3 | E3: Jahr 4 | F3: Jahr 5
A4: Umsatz | B4: ='6_GuV_Breakeven'!B4 -> 97115 | C4: ='6_GuV_Breakeven'!C4 -> 533916.25 | D4: ='6_GuV_Breakeven'!D4 -> 1851023 | E4: ='6_GuV_Breakeven'!E4 -> 4585217 | F4: ='6_GuV_Breakeven'!F4 -> 8675782
A5: Fixkosten | B5: ='4_Kosten'!B14 -> 313000 | C5: ='4_Kosten'!C14 -> 720000 | D5: ='4_Kosten'!D14 -> 1170000 | E5: ='4_Kosten'!E14 -> 1512000 | F5: ='4_Kosten'!F14 -> 1670000
A6: Variable Kosten | B6: ='5_Umsatz_Prognose'!B33 -> 154750.14 | C6: ='5_Umsatz_Prognose'!C33 -> 563918.07 | D6: ='5_Umsatz_Prognose'!D33 -> 1461840.9 | E6: ='5_Umsatz_Prognose'!E33 -> 2746232.1 | F6: ='5_Umsatz_Prognose'!F33 -> 3739396.5
A7: Gesamtkosten | B7: ='4_Kosten'!B26 -> 467750.14 | C7: ='4_Kosten'!C26 -> 1283918.1 | D7: ='4_Kosten'!D26 -> 2631840.9 | E7: ='4_Kosten'!E26 -> 4258232.1 | F7: ='4_Kosten'!F26 -> 5409396.5
A8: EBITDA | B8: ='6_GuV_Breakeven'!B9 -> -370635.14 | C8: ='6_GuV_Breakeven'!C9 -> -750001.82 | D8: ='6_GuV_Breakeven'!D9 -> -780817.87 | E8: ='6_GuV_Breakeven'!E9 -> 326984.91 | F8: ='6_GuV_Breakeven'!F9 -> 3266385.5
A9: Kumulierter EBITDA | B9: ='6_GuV_Breakeven'!B13 -> -370635.14 | C9: ='6_GuV_Breakeven'!C13 -> -1120637 | D9: ='6_GuV_Breakeven'!D13 -> -1901454.8 | E9: ='6_GuV_Breakeven'!E13 -> -1574469.9 | F9: ='6_GuV_Breakeven'!F13 -> 1691915.6
A10: Cash-Bestand | B10: ='6_GuV_Breakeven'!B16 -> 1379364.9 | C10: ='6_GuV_Breakeven'!C16 -> 629363.04 | D10: ='6_GuV_Breakeven'!D16 -> 4848545.2 | E10: ='6_GuV_Breakeven'!E16 -> 5175530.1 | F10: ='6_GuV_Breakeven'!F16 -> 8441915.6
A11: Breakeven-Umsatz | B11: ='6_GuV_Breakeven'!B19 -> -527403.9 | C11: ='6_GuV_Breakeven'!C19 -> -12813212 | D11: ='6_GuV_Breakeven'!D19 -> 5564738.8 | E11: ='6_GuV_Breakeven'!E19 -> 3769932 | F11: ='6_GuV_Breakeven'!F19 -> 2935053.6
